covebackup/__init__.py
covebackup/class_covebackup.py
covebackup-1.0.0.dist-info/METADATA
covebackup-1.0.0.dist-info/WHEEL
covebackup-1.0.0.dist-info/licenses/LICENSE.txt
covebackup-1.0.0.dist-info/RECORD
